Src/Defines.v
`ifndef OPCODES
    `define LOAD        7'b00_000_11
    `define LOAD_FP     7'b00_001_11
    `define custom_0    7'b00_010_11
    `define MISC_MEM    7'b00_011_11
    `define OP_IMM      7'b00_100_11
    `define AUIPC       7'b00_101_11
    `define OP_IMM_32   7'b00_110_11

    `define STORE       7'b01_000_11
    `define STORE_FP    7'b01_001_11
    `define custom_1    7'b01_010_11
    `define AMO         7'b01_011_11
    `define OP          7'b01_100_11
    `define LUI         7'b01_101_11
    `define OP_32       7'b01_110_11

    `define MADD        7'b10_000_11
    `define MSUB        7'b10_001_11
    `define NMSUB       7'b10_010_11
    `define NMADD       7'b10_011_11
    `define OP_FP       7'b10_100_11
    `define custom_2    7'b10_110_11

    `define BRANCH      7'b11_000_11
    `define JALR        7'b11_001_11
    `define JAL         7'b11_011_11
    `define SYSTEM      7'b11_100_11
    `define custom_3    7'b11_110_11
`endif /*OPCODES*/

`ifndef INSTRUCTION_TYPES
    `define R_TYPE 0
    `define I_TYPE 1
    `define S_TYPE 2
    `define B_TYPE 3
    `define U_TYPE 4
    `define J_TYPE 5
`endif /*INSTRUCTION_TYPES*/

`ifndef I_INSTRUCTIONS
    `define ADDI    3'b000
    `define SLTI    3'b010
    `define SLTIU   3'b011
    `define XORI    3'b100
    `define ORI     3'b110
    `define ANDI    3'b111
    `define SLLI    3'b001      // Shift Left Immediate -> Logical
    `define SRI     3'b101      // Shift Right Immediate -> Logical & Arithmetic
`endif /*I_INSTRUCTIONS*/

`ifndef R_INSTRUCTIONS
    `define ADDSUB  3'b000
    `define SLL     3'b001      // Shift Left -> Logical   
    `define SLT     3'b010
    `define SLTU    3'b011    
    `define XOR     3'b100    
    `define SR      3'b101      // Shift Right -> Logical & Arithmetic   
    `define OR      3'b110    
    `define AND     3'b111

    `define ADD     7'b0000000
    `define SUB     7'b0100000
`endif /*R_INSTRUCTIONS*/

`ifndef MUL_DIV_INSTRCUTIONS
    `define MUL     3'b000
    `define MULH    3'b001
    `define MULHSU  3'b010
    `define MULHU   3'b011 

    `define DIV     3'b100
    `define DIVU    3'b101
    `define REM     3'b110
    `define REMU    3'b111

    `define MULDIV  7'b0000001
`endif /*MUL_DIV_INSTRCUTIONS*/

`ifndef BRANCH_INSTRUCTIONS
    `define BEQ  3'b000
    `define BNE  3'b001
    `define BLT  3'b100
    `define BGE  3'b101
    `define BLTU 3'b110
    `define BGEU 3'b111
`endif /*BRANCH_INSTRUCTIONS*/

`ifndef ALU_OPERATIONS
    `define ALU_ADD     3'b000
    `define ALU_SUB     3'b001
    `define ALU_AND     3'b010
    `define ALU_OR      3'b011
    `define ALU_XOR     3'b100
`endif /*ALU_OPERATIONS*/

`ifndef ALU_SRC_SELECT
    `define PC          2'b00
    `define A           2'b01
    `define ALU_RESULT  2'b10

    `define B           2'b00
    `define FOUR        2'b01
    `define IMMEDIATE   2'b10
`endif /*ALU_SRC_SELECT*/

`ifndef REGISTER_FILE_WRITE_SOURCE
    `define MEMORY      2'b00
    `define ALU         2'b01
    `define MULTIPLIER  2'b10
`endif /*REGISTER_FILE_WRITE_SOURCE*/

`ifndef CONTROL_SIGNALS
    `define INSTRUCTION     1'b0
    `define DATA            1'b1

    `define READ            1'b0
    `define WRITE           1'b1

    `define DISABLE         1'b0
    `define ENABLE          1'b1
`endif /*CONTROL_SIGNALS*/

`ifndef CONTROLLER_STATES
    `define RESET            0
    `define FETCH_BEGIN      1
    `define FETCH_WAIT       2
    `define FETCH_DONE       3
    `define DECODE           4
    `define EXECUTE          5
    `define EXECUTE_BRANCH   6
    `define TAKE_BRANCH      7
`endif /*CONTROLLER_STATES*/

Src/Multiplier.v
`include "Defines.v"

module Multiplier
(
    input enable,

    input [31 : 0] operand_1,
    input [31 : 0] operand_2,
    output reg [31 : 0] product
);

    reg [3:0] neg;
    reg [3:0] bit_inverted_1;
    reg [3:0] bit_inverted_2;
    reg [15:0] partial_product_0;
    reg [15:0] partial_product_1;
    reg [15:0] partial_product_2;
    reg [15:0] partial_product_3;
    reg [7:0]product_bits;
    reg [2:0]carry_bits;
    reg [7:0] operand_1_complement;
    reg adjacent_jump;
    reg adjacent_jump_1;
    reg is_negative;
    integer i ;
    integer j ;
    reg [15:0]result;
    reg [7:0]carry_status;
    reg next_adjacent_jump;
    reg next_adjacent_jump_1;
    reg is_negative_result;

    always @(*)
    begin

        if(enable==1) begin
            i = 0;
            j = 0;
            carry_status = 8'b0;
            bit_inverted_1[0] = ~(operand_2[2*0]^0);
            bit_inverted_2[0]= ~(( operand_2[2*0+1] & ~operand_2[2*0] & (~0)  ) | ( (~operand_2[2*0+1]) & (operand_2[2*0]) & 0 ) );
            neg[0] = ((~(0))|(~(operand_2[2*0])))&(operand_2[2*0+1]);
            carry_bits[0] = neg[0] & ( ~operand_1[0] | bit_inverted_1[0]);
                
            bit_inverted_1[1] = ~(operand_2[2*1]^operand_2[2*1-1]);
            bit_inverted_2[1]= ~(( operand_2[2*1+1] & ~operand_2[2*1] & (~operand_2[2*1-1])  ) | ( (~operand_2[2*1+1]) & (operand_2[2*1]) & operand_2[2*1-1] ) );
            neg[1] = ((~(operand_2[2*1-1]))|(~(operand_2[2*1])))&(operand_2[2*1+1]);
            carry_bits[1] = neg[1] & ( ~operand_1[0] | bit_inverted_1[1]);

            bit_inverted_1[2] = ~(operand_2[2*2]^operand_2[2*2-1]);
            bit_inverted_2[2]= ~(( operand_2[2*2+1] & ~operand_2[2*2] & (~operand_2[2*2-1])  ) | ( (~operand_2[2*2+1]) & (operand_2[2*2]) & operand_2[2*2-1] ) );
            neg[2] = ((~(operand_2[2*2-1]))|(~(operand_2[2*2])))&(operand_2[2*2+1]);
            carry_bits[2] = neg[2] & ( ~operand_1[0] | bit_inverted_1[2]);


            bit_inverted_1[3] = ~(operand_2[2*3]^operand_2[2*3-1]);
            bit_inverted_2[3]= ~(( operand_2[2*3+1] & ~operand_2[2*3] & (~operand_2[2*3-1])  ) | ( (~operand_2[2*3+1]) & (operand_2[2*3]) & operand_2[2*3-1] ) );
            neg[3] = ((~(operand_2[2*3-1]))|(~(operand_2[2*3])))&(operand_2[2*3+1]);

            for(i=0;i<=2;++i) begin
                
                for(j=0;j<=7;++j)begin 
                    if (j==0) begin
                        adjacent_jump = operand_1[j];
                        adjacent_jump_1 = 0;
                    end else begin
                        adjacent_jump = operand_1[j];
                        adjacent_jump_1 = operand_1[j-1];
                    end
                    next_adjacent_jump_1 = ~((adjacent_jump_1)^(neg[i]));
                    next_adjacent_jump = ~((adjacent_jump)^(neg[i]));
                    product_bits[j] = ~( (  (bit_inverted_2[i])|( next_adjacent_jump_1  )  )&(   (bit_inverted_1[i])|( next_adjacent_jump )  ) );
                    if(j==7) begin
                        is_negative_result = ~next_adjacent_jump & (~bit_inverted_1[i] | ~bit_inverted_2[i]);
                    end
                end

                product_bits[0] = ~(bit_inverted_1[i]) & operand_1[0];
                

                case (i) //[i][15:0]
                    0 : partial_product_0 = {5'b0, ~is_negative_result ,is_negative_result ,is_negative_result , product_bits[7] ,product_bits[6],product_bits[5],product_bits[4],product_bits[3],product_bits[2],product_bits[1],product_bits[0] };  
                    1 : partial_product_1 = {4'b0,1'b1 ,~is_negative_result , product_bits[7] ,product_bits[6],product_bits[5],product_bits[4],product_bits[3],product_bits[2],product_bits[1],product_bits[0] , carry_bits[i-1],1'b0 };
                    2 : partial_product_2 = {2'b0 ,  1'b1 ,~is_negative_result , product_bits[7] ,product_bits[6],product_bits[5],product_bits[4],product_bits[3],product_bits[2],product_bits[1],product_bits[0] , carry_bits[i-1],1'b0,1'b0,1'b0 };
                endcase
            end
                for(i=0;i<=3;++i) begin
                    if(operand_1[2*i]==1'b1)begin
                        carry_status[2*i] = 1;
                        carry_status[2*i+1] = 1;
                    end else begin
                        if(operand_1[2*i]==1'b1) begin
                            carry_status[2*i] = 0;
                            carry_status[2*i+1] = 1;
                        end else begin
                            carry_status[2*i] = 0;
                            carry_status[2*i+1] = 0;
                        end
                    end
                end
                for(i=0;i<=1;++i) begin
                    if(carry_status[4*i+1]==1)begin
                        carry_status[4*i+2] =1;
                        carry_status[4*i+2] =1;
                    end
                end
                if(carry_status[3]==1) begin
                    carry_status[4]=1;
                    carry_status[5]=1;
                    carry_status[6]=1;
                    carry_status[7]=1;
                end
                is_negative = 0;
                for (i = 0; i<=7;++i ) begin
                    if(is_negative==1'b1) begin
                        operand_1_complement[i] = ~operand_1[i];
                    end else begin
                        operand_1_complement[i] = operand_1[i];
                    end
                    if(carry_status[i]==1'b1) begin
                        is_negative = 1;
                    end
                end

            
            if(neg[3]==1'b1) begin
                neg[3]=0;
                for(j=0;j<=7;++j)begin 
                    if (j==0) begin
                        adjacent_jump = operand_1_complement[j];
                        adjacent_jump_1 = 0;
                    end else begin
                        adjacent_jump = operand_1_complement[j];
                        adjacent_jump_1 = operand_1_complement[j-1];
                    end
                    product_bits[j] = ~( (  (bit_inverted_2[3])|(~((adjacent_jump_1)^(neg[3])))  )&(   (bit_inverted_1[3])|(~((adjacent_jump)^(neg[3])))  ) );
                end

                
                partial_product_3 = {  1'b1 ,~product_bits[7] , product_bits[7] ,product_bits[6],product_bits[5],product_bits[4],product_bits[3],product_bits[2],product_bits[1],product_bits[0] , carry_bits[2],1'b0,1'b0,1'b0 ,1'b0,1'b0};          
            end else begin
                for(j=0;j<=7;++j)begin 
                    if (j==0) begin
                        adjacent_jump = operand_1[j];
                        adjacent_jump_1 = 0;
                    end else begin
                        adjacent_jump = operand_1[j];
                        adjacent_jump_1 = operand_1[j-1];
                    end
                    product_bits[j] = ~( (  (bit_inverted_2[3])|(~((adjacent_jump_1)^(neg[3])))  )&(   (bit_inverted_1[3])|(~((adjacent_jump)^(neg[3])))  ) );
                end

                product_bits[0] = ~(bit_inverted_1[3]) & operand_1[0];
                partial_product_3 = {  1'b1 ,~product_bits[7] , product_bits[7] ,product_bits[6],product_bits[5],product_bits[4],product_bits[3],product_bits[2],product_bits[1],product_bits[0] , carry_bits[2],1'b0,1'b0,1'b0 ,1'b0,1'b0};                 
            end
            result = partial_product_0 + partial_product_1 + partial_product_2 + partial_product_3;
            product = {   {16{result[15]}}  ,result};
            end
    end 
    

endmodule

Src/Multiplier_tb.v
`timescale 1ns/1ns
`include "Multiplier.v"

module Multiplier_tb;

    parameter test_num = 10;
    reg [31:0] oper_1;
    reg [31:0] oper_2;
    reg [7:0] oper_3;
    reg [7:0] oper_4;
    reg en = 1;
    integer i = 0;
    Multiplier uut(
        .operand_1(oper_1),.operand_2(oper_2),.enable(en)
    );

    initial begin
        $dumpfile("Multiplier.vcd");
        $dumpvars(0,Multiplier_tb);
        for (i = 0;i<test_num;i=i+1) begin
            oper_3  =$random;
            oper_4  =$random;
            oper_1 = oper_3;
            oper_2 = oper_4;
            #1;
        end

    end

    
endmodule

Src/Multiplier.vcd
$date
	Sun Jan 14 21:56:25 2024
$end
$version
	Icarus Verilog
$end
$timescale
	1ns
$end
$scope module Multiplier_tb $end
$var reg 1 ! en $end
$var reg 32 " oper_1 [31:0] $end
$var reg 32 # oper_2 [31:0] $end
$var reg 8 $ oper_3 [7:0] $end
$var reg 8 % oper_4 [7:0] $end
$var integer 32 & i [31:0] $end
$scope module uut $end
$var wire 1 ! enable $end
$var wire 32 ' operand_1 [31:0] $end
$var wire 32 ( operand_2 [31:0] $end
$var reg 1 ) adjacent_jump $end
$var reg 1 * adjacent_jump_1 $end
$var reg 4 + bit_inverted_1 [3:0] $end
$var reg 4 , bit_inverted_2 [3:0] $end
$var reg 3 - carry_bits [2:0] $end
$var reg 8 . carry_status [7:0] $end
$var reg 1 / is_negative $end
$var reg 1 0 is_negative_result $end
$var reg 4 1 neg [3:0] $end
$var reg 1 2 next_adjacent_jump $end
$var reg 1 3 next_adjacent_jump_1 $end
$var reg 8 4 operand_1_complement [7:0] $end
$var reg 16 5 partial_product_0 [15:0] $end
$var reg 16 6 partial_product_1 [15:0] $end
$var reg 16 7 partial_product_2 [15:0] $end
$var reg 16 8 partial_product_3 [15:0] $end
$var reg 32 9 product [31:0] $end
$var reg 8 : product_bits [7:0] $end
$var reg 16 ; result [15:0] $end
$var integer 32 < i [31:0] $end
$var integer 32 = j [31:0] $end
$upscope $end
$upscope $end
$enddefinitions $end
#0
$dumpvars
b1000 =
b1000 <
b1110111000100100 ;
b10111000 :
b11111111111111111110111000100100 9
b1010111000000000 8
b11000000000000 7
b110000000000 6
b10000100100 5
b11011100 4
13
12
b0 1
00
1/
b11111100 .
b0 -
b111 ,
b1110 +
1*
1)
b10000001 (
b100100 '
b0 &
b10000001 %
b100100 $
b10000001 #
b100100 "
1!
$end
#1
b1101111011 9
b1101111011 ;
b1100010010100000 8
b11110111 4
1/
b10111011000000 7
b110000100100 6
b1111110111 5
10
b10010 :
02
0)
03
0*
b100 -
b11 ,
b1100 +
b101 1
b111 .
b1000 =
b1000 <
b1100011 #
b1100011 (
b1001 "
b1001 '
b1100011 %
b1001 $
b1 &
#2
b11111111111111111111101000101001 9
b1111101000101001 ;
b1011100110000000 8
b11110011 4
1/
b11000011010000 7
b101111001100 6
b10000001101 5
00
12
1*
b11100110 :
13
1)
b0 -
b111 ,
b1000 +
b10 1
b11111111 .
b1000 =
b1000 <
b10001101 #
b10001101 (
b1101 "
b1101 '
b10001101 %
b1101 $
b10 &
#3
b11100011010 9
b11100011010 ;
b1100000000000000 8
b10011011 4
1/
b11011001010000 7
b110110010110 6
b1100110100 5
00
12
0)
b0 :
03
1*
b1 -
b1 1
b1110 ,
b1001 +
b11111111 .
b1000 =
b1000 <
b10010 #
b10010 (
b1100101 "
b1100101 '
b10010 %
b1100101 $
b11 &
#4
b1101 9
b1101 ;
b11111111 4
1/
b11000000010000 7
b101111111100 6
00
b10000000001 5
b0 :
12
13
0*
0)
b0 -
b10 1
b1111 ,
b1000 +
b111 .
b1000 =
b1000 <
b1101 #
b1101 (
b1 "
b1 '
b1101 %
b1 $
b100 &
#5
b1110000011110 9
b1110000011110 ;
b1101110110000000 8
b10001110 4
1/
b11000000001000 7
b101000100000 6
00
b10001110110 5
03
1*
b1110110 :
12
0)
b100 +
b10 -
b11111100 .
b1000 =
b1000 <
b111101 #
b111101 (
b1110110 "
b1110110 '
b111101 %
b1110110 $
b101 &
#6
b100010011100 9
b100010011100 ;
b1100100110000000 8
b10011 4
1/
b10111011010000 7
10
b110001001100 6
b10000000000 5
b100110 :
02
03
0*
0)
b10 1
b111 ,
b0 -
b1001 +
b11111111 .
b1000 =
b1000 <
b10001100 #
b10001100 (
b11101101 "
b11101101 '
b10001100 %
b11101101 $
b110 &
#7
b110010110 9
b110010110 ;
b1100000111000000 8
b111 4
1/
b11000000000000 7
b101111001010 6
b10000001100 5
00
03
0*
b111 :
02
0)
b111 +
b1 -
b1 1
b1100 ,
b11110111 .
b1000 =
b1000 <
b11000110 #
b11000110 (
b11111001 "
b11111001 '
b11000110 %
b11111001 $
b111 &
#8
b1001111010010 9
b1001111010010 ;
b1100111011000000 8
b111011 4
1/
b11001110110000 7
b110011101110 6
b10001110100 5
b111011 :
13
0*
12
0)
b111 1
b1110 ,
b1 +
b11111111 .
b1000 =
b1000 <
b10101010 #
b10101010 (
b11000101 "
b11000101 '
b10101010 %
b11000101 $
b1000 &
#9
b11111111111111111111001101110011 9
b1111001101110011 ;
b1011001010000000 8
b11011 4
1/
b11000110110000 7
b101100101000 6
00
b10000011011 5
12
1*
b11001010 :
13
1)
b101 1
b0 -
b101 ,
b1010 +
b11111111 .
b1000 =
b1000 <
b1110111 #
b1110111 (
b11100101 "
b11100101 '
b1110111 %
b11100101 $
b1001 &
#10
b1010 &
